LICENSE
MANIFEST.in
README.rst
setup.py
Xymon.egg-info/PKG-INFO
Xymon.egg-info/SOURCES.txt
Xymon.egg-info/dependency_links.txt
Xymon.egg-info/top_level.txt
xymon/__init__.py