Metadata-Version: 1.0
Name: Xymon
Version: 1.0.0
Summary: Update and query statuses on a Xymon server
Home-page: https://github.com/skurfer/python-xymon
Author: Rob McBroom
Author-email: pypi [at] skurfer.com
License: Don't Be a Dick
Platform: UNKNOWN
